[{"symbol": "btc", "price": 70400, "change": -0.37402}, {"symbol": "eth", "price": 2065.7, "change": 0.05686}, {"symbol": "usdt", "price": 1.0, "change": 0.00153}, {"symbol": "bnb", "price": 651.85, "change": 0.04384}, {"symbol": "xrp", "price": 1.38, "change": -0.9998}, {"symbol": "usdc", "price": 0.999999, "change": 0.00683}, {"symbol": "sol", "price": 86.67, "change": -0.71502}, {"symbol": "trx", "price": 0.289466, "change": -0.60446}, {"symbol": "figr_heloc", "price": 1.031, "change": -0.09921}, {"symbol": "doge", "price": 0.094538, "change": 1.15411}, {"symbol": "wbt", "price": 55.5, "change": -1.28685}, {"symbol": "usds", "price": 1.0, "change": 0.00451}, {"symbol": "ada", "price": 0.262657, "change": -0.53855}, {"symbol": "bch", "price": 455.61, "change": -0.44276}, {"symbol": "hype", "price": 37.67, "change": 3.26335}, {"symbol": "leo", "price": 9.07, "change": -0.97935}, {"symbol": "xmr", "price": 351.63, "change": -0.05245}, {"symbol": "link", "price": 9.02, "change": -0.58627}, {"symbol": "usde", "price": 0.999873, "change": 0.03185}, {"symbol": "cc", "price": 0.145894, "change": -1.83701}, {"symbol": "xlm", "price": 0.159499, "change": -0.18334}, {"symbol": "usd1", "price": 0.999254, "change": -0.02448}, {"symbol": "rain", "price": 0.00901695, "change": -0.07014}, {"symbol": "dai", "price": 0.999907, "change": -0.00777}, {"symbol": "ltc", "price": 54.32, "change": -0.95827}, {"symbol": "avax", "price": 9.57, "change": -0.96763}, {"symbol": "pyusd", "price": 0.999965, "change": 0.05393}, {"symbol": "hbar", "price": 0.094352, "change": 0.29588}, {"symbol": "sui", "price": 0.975713, "change": -0.74388}, {"symbol": "zec", "price": 210.69, "change": -0.33046}, {"symbol": "shib", "price": 5.89e-06, "change": 1.16893}, {"symbol": "ton", "price": 1.31, "change": -1.21701}, {"symbol": "cro", "price": 0.075545, "change": -0.30312}, {"symbol": "xaut", "price": 5084.78, "change": -0.72373}, {"symbol": "wlfi", "price": 0.101405, "change": -0.64586}, {"symbol": "paxg", "price": 5119.32, "change": -0.86997}, {"symbol": "m", "price": 1.46, "change": 2.56868}, {"symbol": "dot", "price": 1.5, "change": -1.70029}, {"symbol": "pi", "price": 0.25799, "change": 11.06183}, {"symbol": "uni", "price": 3.91, "change": 0.11986}, {"symbol": "mnt", "price": 0.714873, "change": 2.15622}, {"symbol": "usyc", "price": 1.12, "change": -0.00022}, {"symbol": "tao", "price": 214.77, "change": 8.01449}, {"symbol": "buidl", "price": 1.0, "change": 0.0}, {"symbol": "okb", "price": 94.82, "change": -0.71735}, {"symbol": "sky", "price": 0.080512, "change": 3.7316}, {"symbol": "usdf", "price": 0.997863, "change": 0.03349}, {"symbol": "usdg", "price": 1.0, "change": 0.02393}, {"symbol": "aster", "price": 0.707216, "change": 0.26611}, {"symbol": "near", "price": 1.34, "change": 3.38147}, {"symbol": "aave", "price": 110.12, "change": -1.78772}, {"symbol": "rlusd", "price": 0.999842, "change": 0.01379}, {"symbol": "bgb", "price": 2.15, "change": -1.04455}, {"symbol": "htx", "price": 1.6e-06, "change": -0.08146}, {"symbol": "icp", "price": 2.63, "change": 0.38589}, {"symbol": "pepe", "price": 3.33e-06, "change": -0.774}, {"symbol": "bfusd", "price": 0.999295, "change": -0.01047}, {"symbol": "usdy", "price": 1.12, "change": 0.89563}, {"symbol": "etc", "price": 8.22, "change": -1.09001}, {"symbol": "ondo", "price": 0.25737, "change": 0.08784}, {"symbol": "pump", "price": 0.00209347, "change": 2.63594}, {"symbol": "gt", "price": 7.02, "change": -0.373}, {"symbol": "ustb", "price": 11.02, "change": 0.00961}, {"symbol": "morpho", "price": 1.97, "change": 1.15572}, {"symbol": "kcs", "price": 7.98, "change": -1.37901}, {"symbol": "pol", "price": 0.098191, "change": 0.92022}, {"symbol": "wld", "price": 0.35365, "change": -1.25313}, {"symbol": "eutbl", "price": 1.21, "change": -0.42014}, {"symbol": "qnt", "price": 63.13, "change": 0.93233}, {"symbol": "nexo", "price": 0.906398, "change": -0.23645}, {"symbol": "atom", "price": 1.82, "change": -0.97785}, {"symbol": "ena", "price": 0.105806, "change": 0.88352}, {"symbol": "render", "price": 1.62, "change": 5.95338}, {"symbol": "usdtb", "price": 0.999734, "change": -0.01809}, {"symbol": "kas", "price": 0.03050526, "change": -0.15522}, {"symbol": "night", "price": 0.04739946, "change": 3.04034}, {"symbol": "algo", "price": 0.087467, "change": 1.30112}, {"symbol": "hash", "price": 0.01372135, "change": -1.14609}, {"symbol": "usdd", "price": 1.0, "change": 0.01707}, {"symbol": "flr", "price": 0.00888331, "change": -1.31569}, {"symbol": "ousg", "price": 114.56, "change": 0.00925}, {"symbol": "apt", "price": 0.911879, "change": -2.7913}, {"symbol": "jtrsy", "price": 1.097, "change": 0.00848}, {"symbol": "fil", "price": 0.862973, "change": -2.05569}, {"symbol": "xdc", "price": 0.03281062, "change": 2.12968}, {"symbol": "trump", "price": 2.79, "change": -5.53271}, {"symbol": "vet", "price": 0.00713324, "change": 0.14039}, {"symbol": "bdx", "price": 0.080495, "change": 0.4055}, {"symbol": "stable", "price": 0.02870125, "change": -2.72727}, {"symbol": "ylds", "price": 0.999997, "change": -0.00023}, {"symbol": "arb", "price": 0.099543, "change": -1.46781}, {"symbol": "gho", "price": 0.999652, "change": -0.05946}, {"symbol": "jup", "price": 0.161929, "change": -2.39658}, {"symbol": "usd0", "price": 0.995451, "change": 0.19774}, {"symbol": "bonk", "price": 5.99e-06, "change": -0.18577}, {"symbol": "tusd", "price": 0.999448, "change": -0.01616}, {"symbol": "a7a5", "price": 0.01247063, "change": -0.89664}, {"symbol": "ftn", "price": 1.089, "change": 0.02983}, {"symbol": "jst", "price": 0.053479, "change": 1.42664}, {"symbol": "dcr", "price": 27.05, "change": -5.50996}, {"symbol": "virtual", "price": 0.709967, "change": 1.54567}, {"symbol": "stx", "price": 0.25324, "change": -1.47193}, {"symbol": "cake", "price": 1.39, "change": 0.73453}, {"symbol": "pengu", "price": 0.00715297, "change": 0.00633}, {"symbol": "kite", "price": 0.249665, "change": -5.05536}, {"symbol": "eurc", "price": 1.15, "change": -0.37923}, {"symbol": "ethfi", "price": 0.571963, "change": -0.11027}, {"symbol": "sei", "price": 0.063164, "change": 1.20329}, {"symbol": "siren", "price": 0.574746, "change": 9.77372}, {"symbol": "jaaa", "price": 1.026, "change": 0.0433}, {"symbol": "dash", "price": 32.74, "change": 0.78112}, {"symbol": "zro", "price": 2.01, "change": -5.44077}, {"symbol": "kau", "price": 164.92, "change": -0.72212}, {"symbol": "xtz", "price": 0.362406, "change": -0.06322}, {"symbol": "chz", "price": 0.0372311, "change": -3.1049}, {"symbol": "fdusd", "price": 0.99996, "change": -0.05082}, {"symbol": "usx", "price": 0.999877, "change": 0.01127}, {"symbol": "river", "price": 18.64, "change": 27.42263}, {"symbol": "fet", "price": 0.161068, "change": 2.20667}, {"symbol": "pippin", "price": 0.353117, "change": 1.06445}, {"symbol": "crv", "price": 0.235041, "change": -1.42409}, {"symbol": "adi", "price": 3.47, "change": 3.07462}, {"symbol": "gno", "price": 127.63, "change": -0.86965}, {"symbol": "nft", "price": 3.35008e-07, "change": 0.2124}, {"symbol": "usdai", "price": 1.0, "change": 0.00353}, {"symbol": "prime", "price": 1.025, "change": -0.00853}, {"symbol": "btt", "price": 3.26453e-07, "change": -0.78087}, {"symbol": "kaia", "price": 0.054361, "change": -0.37823}, {"symbol": "aero", "price": 0.3373, "change": -1.03205}, {"symbol": "sun", "price": 0.01598185, "change": -0.0242}, {"symbol": "inj", "price": 3.0, "change": 0.4644}, {"symbol": "tia", "price": 0.333685, "change": -0.35753}, {"symbol": "bsv", "price": 14.8, "change": -2.76062}, {"symbol": "floki", "price": 2.976e-05, "change": 0.72395}, {"symbol": "spx", "price": 0.308273, "change": 0.89343}, {"symbol": "jasmy", "price": 0.005789, "change": 1.27963}, {"symbol": "grt", "price": 0.02662234, "change": 3.3764}, {"symbol": "syrup", "price": 0.246426, "change": 8.04113}, {"symbol": "ip", "price": 0.786988, "change": 1.12553}, {"symbol": "lit", "price": 1.1, "change": 6.88534}, {"symbol": "iota", "price": 0.063704, "change": 0.79179}, {"symbol": "frax", "price": 0.992483, "change": 0.04296}, {"symbol": "2z", "price": 0.078794, "change": 1.44012}, {"symbol": "cfx", "price": 0.052558, "change": 2.45802}, {"symbol": "btse", "price": 1.66, "change": 3.90904}, {"symbol": "pyth", "price": 0.0468473, "change": 0.83958}, {"symbol": "ohm", "price": 17.01, "change": -1.17289}, {"symbol": "fo", "price": 0.265906, "change": -0.9433}, {"symbol": "crvusd", "price": 0.998607, "change": 0.51194}, {"symbol": "vvv", "price": 5.88, "change": -0.42967}, {"symbol": "bard", "price": 1.16, "change": 6.82347}, {"symbol": "ldo", "price": 0.297961, "change": -1.0523}, {"symbol": "op", "price": 0.117569, "change": -2.11773}, {"symbol": "great", "price": 11.8, "change": -0.022}, {"symbol": "tel", "price": 0.00255209, "change": -2.20109}, {"symbol": "h", "price": 0.132767, "change": -1.56487}, {"symbol": "xpl", "price": 0.107453, "change": 9.63626}, {"symbol": "mon", "price": 0.02146397, "change": 0.27298}, {"symbol": "ens", "price": 6.03, "change": -0.4969}, {"symbol": "uds", "price": 1.85, "change": 1.24925}, {"symbol": "apepe", "price": 1.09e-06, "change": -0.24378}, {"symbol": "nusd", "price": 0.998675, "change": 0.17519}, {"symbol": "lunc", "price": 4.128e-05, "change": -0.18837}, {"symbol": "strk", "price": 0.04051157, "change": 0.97317}, {"symbol": "sand", "price": 0.081948, "change": -0.89674}, {"symbol": "usda", "price": 0.984174, "change": 0.00625}, {"symbol": "ausd", "price": 1.0, "change": 0.01498}, {"symbol": "hnt", "price": 1.16, "change": -3.25434}, {"symbol": "ab", "price": 0.00214733, "change": -0.95778}, {"symbol": "twt", "price": 0.501725, "change": 2.90535}, {"symbol": "bcap", "price": 22.87, "change": 0.0}, {"symbol": "pendle", "price": 1.26, "change": -1.99637}, {"symbol": "ustbl", "price": 1.077, "change": 0.0}, {"symbol": "9bit", "price": 0.02491806, "change": 7.16859}, {"symbol": "dexe", "price": 4.25, "change": -0.20772}, {"symbol": "zbcn", "price": 0.00202892, "change": 0.20094}, {"symbol": "grass", "price": 0.365101, "change": 2.19133}, {"symbol": "borg", "price": 0.199266, "change": 0.83695}, {"symbol": "xcn", "price": 0.00522774, "change": 3.02043}, {"symbol": "axs", "price": 1.13, "change": -1.27394}, {"symbol": "pc0000031", "price": 1.0, "change": 0.0}, {"symbol": "cvx", "price": 2.06, "change": -6.47112}, {"symbol": "wfi", "price": 2.32, "change": 3.27012}, {"symbol": "vsn", "price": 0.051383, "change": -0.05468}, {"symbol": "real", "price": 0.058209, "change": 0.79596}, {"symbol": "neo", "price": 2.6, "change": 0.446}, {"symbol": "b", "price": 0.179186, "change": -3.64177}, {"symbol": "ft", "price": 0.09806, "change": -0.17481}, {"symbol": "fdit", "price": 1.0, "change": 0.0}, {"symbol": "theta", "price": 0.177581, "change": -4.01958}, {"symbol": "wal", "price": 0.079108, "change": 1.29453}, {"symbol": "zk", "price": 0.01918312, "change": 1.73088}, {"symbol": "fluid", "price": 2.25, "change": 1.59798}, {"symbol": "mana", "price": 0.091003, "change": -1.71016}, {"symbol": "comp", "price": 17.93, "change": -5.01183}, {"symbol": "ff", "price": 0.074016, "change": 0.05651}, {"symbol": "iusd", "price": 0.999745, "change": -0.02033}, {"symbol": "wif", "price": 0.167046, "change": -0.72444}, {"symbol": "ultima", "price": 4397.8, "change": -3.98781}, {"symbol": "mx", "price": 1.79, "change": -0.13251}]